{
	"animations": [
		{
			"offsets": [
				-9,
				10
			],
			"loop": false,
			"fps": 24,
			"anim": "singLEFT",
			"indices": [],
			"name": "LEFT"
		},
		{
			"loop": false,
			"offsets": [
				-6,
				0
			],
			"anim": "singUP",
			"fps": 24,
			"name": "UP",
			"indices": []
		},
		{
			"loop": false,
			"offsets": [
				-5,
				0
			],
			"anim": "singRIGHT",
			"fps": 25,
			"name": "RIGHT",
			"indices": []
		},
		{
			"loop": false,
			"offsets": [
				0,
				14
			],
			"anim": "singDOWN",
			"fps": 24,
			"name": "DOWN",
			"indices": []
		},
		{
			"offsets": [
				0,
				0
			],
			"indices": [],
			"fps": 24,
			"anim": "idle",
			"loop": false,
			"name": "IDLE"
		}
	],
	"no_antialiasing": false,
	"image": "characters/bendu",
	"position": [
		10,
		30
	],
	"healthicon": "bendu",
	"flip_x": false,
	"healthbar_colors": [
		255,
		255,
		0
	],
	"camera_position": [
		0,
		0
	],
	"sing_duration": 6.1,
	"scale": 1.2
}